aws_network_firewall/__init__.py
aws_network_firewall/account.py
aws_network_firewall/cidr_range.py
aws_network_firewall/cidr_ranges.py
aws_network_firewall/cli/__init__.py
aws_network_firewall/cli/commands/__init__.py
aws_network_firewall/cli/commands/check.py
aws_network_firewall/cli/commands/docs.py
aws_network_firewall/cli/commands/update.py
aws_network_firewall/cli/handler.py
aws_network_firewall/destination.py
aws_network_firewall/documentation_generator.py
aws_network_firewall/engines/__init__.py
aws_network_firewall/engines/abstract.py
aws_network_firewall/engines/default_rule.py
aws_network_firewall/engines/dns_rule.py
aws_network_firewall/engines/icmp_rule.py
aws_network_firewall/engines/prefix_list.py
aws_network_firewall/engines/tls_rule.py
aws_network_firewall/rule.py
aws_network_firewall/rule_set.py
aws_network_firewall/schemas/__init__.py
aws_network_firewall/schemas/environment.yaml
aws_network_firewall/sid_state.py
aws_network_firewall/source.py
aws_network_firewall/suricata/__init__.py
aws_network_firewall/suricata/host.py
aws_network_firewall/suricata/option.py
aws_network_firewall/suricata/rule.py
aws_network_firewall-0.10.2.dist-info/LICENSE.txt
aws_network_firewall-0.10.2.dist-info/METADATA
aws_network_firewall-0.10.2.dist-info/WHEEL
aws_network_firewall-0.10.2.dist-info/entry_points.txt
aws_network_firewall-0.10.2.dist-info/RECORD
